Metadata-Version: 2.1
Name: litAPI
Version: 0.0
Summary: API for https://www.lit.msu.ru/
Home-page: UNKNOWN
Author-email: gr.eydelkind@gmail.com
License: UNKNOWN
Platform: UNKNOWN
